aioecopanel/__init__.py
aioecopanel/aioecopanel.py
aioecopanel/const.py
aioecopanel/exceptions.py
aioecopanel/models.py
aioecopanel-0.0.14.dist-info/LICENSE.txt
aioecopanel-0.0.14.dist-info/METADATA
aioecopanel-0.0.14.dist-info/WHEEL
aioecopanel-0.0.14.dist-info/top_level.txt
aioecopanel-0.0.14.dist-info/RECORD
