Metadata-Version: 2.1
Name: aioecopanel
Version: 0.0.14
Summary: A package to be used for the Home Assistant Bepacom Integration for displaying BACnet devices.
Author-email: Luuk Geertsema <s1136643@windesheim.nl>
Project-URL: Homepage, https://github.com/pypa/sampleproject
Project-URL: Bug Tracker, https://github.com/pypa/sampleproject/issues
Classifier: Programming Language :: Python :: 3
Classifier: License :: OSI Approved :: MIT License
Classifier: Operating System :: OS Independent
Requires-Python: >=3.10
License-File: LICENSE.txt
